{
  "project_info": {
    "project_number": "717096557568",
    "firebase_url": "https://sikegi-e5929-default-rtdb.firebaseio.com",
    "project_id": "sikegi-e5929",
    "storage_bucket": "sikegi-e5929.firebasestorage.app"
  },
  "client": [
    {
      "client_info": {
        "mobilesdk_app_id": "1:717096557568:android:12f26b745bff152c9d4ce5",
        "android_client_info": {
          "package_name": "com.example.sikegi_firebase"
        }
      },
      "oauth_client": [],
      "api_key": [
        {
          "current_key": "AIzaSyD2MHfi2QsK6ExX1KdmStbeAMxnUbO93VM"
        }
      ],
      "services": {
        "appinvite_service": {
          "other_platform_oauth_client": []
        }
      }
    },
    {
      "client_info": {
        "mobilesdk_app_id": "1:717096557568:android:9fc4f4a5dc6d7ddc9d4ce5",
        "android_client_info": {
          "package_name": "com.example.uas_praktikummobileprogramming"
        }
      },
      "oauth_client": [],
      "api_key": [
        {
          "current_key": "AIzaSyD2MHfi2QsK6ExX1KdmStbeAMxnUbO93VM"
        }
      ],
      "services": {
        "appinvite_service": {
          "other_platform_oauth_client": []
        }
      }
    }
  ],
  "configuration_version": "1"
}